energyplus/__init__.py
energyplus-0.0.1.dist-info/LICENSE
energyplus-0.0.1.dist-info/METADATA
energyplus-0.0.1.dist-info/WHEEL
energyplus-0.0.1.dist-info/top_level.txt
energyplus-0.0.1.dist-info/RECORD
