Metadata-Version: 2.1
Name: energyplus
Version: 0.0.1
Summary: EnergyPlus API Python Bindings
Home-page: https://github.com/myoldmopar/energyplusapi
Author: Edwin Lee
Author-email: edwin@dummy.org
License: UNKNOWN
Platform: UNKNOWN
Classifier: Programming Language :: Python :: 3
Classifier: License :: OSI Approved :: MIT License
Classifier: Operating System :: OS Independent
Requires-Python: >=3.5
